<Properties StartupConfiguration="{E885DBF4-A701-A697-42D5-2B48B03E4212}|">
  <MonoDevelop.Ide.DebuggingService.PinnedWatches />
  <MonoDevelop.Ide.Workbench ActiveDocument="Assets/Scripts/UI/UIManager.cs">
    <Files>
      <File FileName="Assets/Scripts/Functionality/SlotBehaviour.cs" Line="513" Column="39" />
      <File FileName="Assets/Scripts/Functionality/BonusController.cs" Line="17" Column="37" />
      <File FileName="Assets/Scripts/APIs/SocketIOManager.cs" Line="40" Column="86" />
      <File FileName="Assets/Scripts/UI/UIManager.cs" Line="475" Column="80" />
      <File FileName="Assets/Scripts/Functionality/PayoutCalculation.cs" Line="43" Column="30" />
      <File FileName="Assets/Scripts/Functionality/AutoSpinManager.cs" Line="1" Column="1" />
      <File FileName="Assets/Scripts/Functionality/Stopper.cs" Line="1" Column="1" />
      <File FileName="Assets/Scripts/Functionality/editorRunOnly.cs" Line="11" Column="64" />
    </Files>
    <Pads>
      <Pad Id="ProjectPad">
        <State name="__root__">
          <Node name="SlotMS_Lucky777" expanded="True">
            <Node name="Assets" expanded="True">
              <Node name="com.unity.uiextensions" expanded="True">
                <Node name="Runtime" expanded="True">
                  <Node name="Scripts" expanded="True">
                    <Node name="Primitives" expanded="True" />
                  </Node>
                </Node>
              </Node>
              <Node name="Scripts" expanded="True">
                <Node name="APIs" expanded="True" />
                <Node name="Functionality" expanded="True" />
                <Node name="UI" expanded="True" />
              </Node>
            </Node>
            <Node name="Packages" expanded="True">
              <Node name="com.tivadar.best.http" expanded="True">
                <Node name="Runtime" expanded="True">
                  <Node name="Shared" expanded="True">
                    <Node name="Logger" expanded="True" />
                  </Node>
                </Node>
              </Node>
            </Node>
          </Node>
        </State>
      </Pad>
    </Pads>
  </MonoDevelop.Ide.Workbench>
  <MonoDevelop.Ide.Workspace ActiveConfiguration="Debug" />
  <MonoDevelop.Ide.DebuggingService.Breakpoints>
    <BreakpointStore />
  </MonoDevelop.Ide.DebuggingService.Breakpoints>
  <MultiItemStartupConfigurations />
  <MonoDevelop.Ide.ItemProperties.Assembly-CSharp PreferredExecutionTarget="43c28c8c-974a-456f-9db6-72712e8c32af" />
</Properties>